izroq_fab_sm/__init__.py
izroq_fab_sm-0.1.dist-info/METADATA
izroq_fab_sm-0.1.dist-info/WHEEL
izroq_fab_sm-0.1.dist-info/top_level.txt
izroq_fab_sm-0.1.dist-info/RECORD
